story_clustering/__init__.py
story_clustering/__main__.py
story_clustering/clustering.py
story_clustering/document_representation.py
story_clustering/event_organizer.py
story_clustering/eventdetector.py
story_clustering/keywords_organizer.py
story_clustering/nlp_utils.py
story_clustering/tests/__init__.py
story_clustering/tests/clustered_news_item_list.json
story_clustering/tests/conftest.py
story_clustering/tests/news_item_list.json
story_clustering/tests/test_clustering.py
story_clustering/tests/testdata.py
taranis_story_clustering-0.8.1.dist-info/LICENSE.md
taranis_story_clustering-0.8.1.dist-info/METADATA
taranis_story_clustering-0.8.1.dist-info/WHEEL
taranis_story_clustering-0.8.1.dist-info/top_level.txt
taranis_story_clustering-0.8.1.dist-info/RECORD
