Metadata-Version: 2.1
Name: taranis_story_clustering
Version: 0.8.1
Summary: Story Clustering Bot for Taranis AI
Maintainer-email: AIT <benjamin.akhras@ait.ac.at>
License: EUROPEAN UNION PUBLIC LICENCE v. 1.2
Project-URL: Source Code, https://github.com/taranis-ai/story-clustering
Classifier: Programming Language :: Python
Classifier: Programming Language :: Python :: 3
Classifier: Programming Language :: Python :: 3.10
Classifier: Programming Language :: Python :: 3.11
Classifier: Programming Language :: Python :: 3.12
Classifier: Topic :: Security
Requires-Python: >=3.11
License-File: LICENSE.md
Requires-Dist: sentence-transformers
Requires-Dist: transformers
Requires-Dist: typing-extensions
Requires-Dist: torch
Requires-Dist: nltk
Requires-Dist: numpy
Requires-Dist: networkx
Requires-Dist: polyfuzz
Requires-Dist: pytest
Provides-Extra: dev
Requires-Dist: pytest ; extra == 'dev'
Requires-Dist: ruff ; extra == 'dev'
